{
    "outputs": [
        {
            "panel_label": "A",
            "is_a_plot": "no",
            "units_provided": null,
            "justify_why_units_are_missing": null,
            "unit_definition_as_provided": null
        },
        {
            "panel_label": "B",
            "is_a_plot": "no",
            "units_provided": null,
            "justify_why_units_are_missing": null,
            "unit_definition_as_provided": null
        },
        {
            "panel_label": "C top",
            "is_a_plot": "yes",
            "units_provided": [
                {
                    "axis": "x",
                    "answer": "not needed"
                },
                {
                    "axis": "y",
                    "answer": "not needed"
                }
            ],
            "justify_why_units_are_missing": null,
            "unit_definition_as_provided": null
        },
        {
            "panel_label": "C bottom",
            "is_a_plot": "yes",
            "units_provided": [
                {
                    "axis": "x",
                    "answer": "not needed"
                },
                {
                    "axis": "y",
                    "answer": true
                },
                {
                    "axis": "z",
                    "answer": "not needed"
                }
            ],
            "justify_why_units_are_missing": null,
            "unit_definition_as_provided": [
                {
                    "axis": "y",
                    "defintion": "Polyp diameter (mm)"
                }
            ]
        },
        {
            "panel_label": "D",
            "is_a_plot": "yes",
            "units_provided": [
                {
                    "axis": "x",
                    "answer": true
                },
                {
                    "axis": "y",
                    "answer": "not needed"
                }
            ],
            "justify_why_units_are_missing": null,
            "unit_definition_as_provided": [
                {
                    "axis": "x",
                    "definition": "Time after birth (months)"
                }
            ]
        },
        {
            "panel_label": "E",
            "is_a_plot": "yes",
            "units_provided": [
                {
                    "axis": "x",
                    "answer": "not needed"
                },
                {
                    "axis": "y",
                    "answer": "not needed"
                }
            ],
            "justify_why_units_are_missing": null,
            "unit_definition_as_provided": null
        },
        {
            "panel_label": "F",
            "is_a_plot": "no",
            "units_provided": null,
            "justify_why_units_are_missing": null,
            "unit_definition_as_provided": null
        },
        {
            "panel_label": "G",
            "is_a_plot": "yes",
            "units_provided": [
                {
                    "axis": "x",
                    "answer": "not needed"
                },
                {
                    "axis": "y",
                    "answer": "not needed"
                }
            ],
            "justify_why_units_are_missing": null,
            "unit_definition_as_provided": null
        }
    ],
    "updated_at": "2025-04-30 17:02:23"
}